lavague/_bundle/__init__.py
lavague-1.1.18.dist-info/LICENSE
lavague-1.1.18.dist-info/METADATA
lavague-1.1.18.dist-info/WHEEL
lavague-1.1.18.dist-info/RECORD
