Metadata-Version: 2.1
Name: lavague
Version: 1.1.18
Summary: automation code generation from text instructions
Home-page: https://mithrilsecurity.io
License: Apache-2.0
Keywords: LAM,action,automation,LLM,NLP,RAG,selenium,playwright
Author: lavague-ai
Requires-Python: >=3.10.0,<4.0.0
Classifier: Development Status :: 3 - Alpha
Classifier: Intended Audience :: Developers
Classifier: License :: OSI Approved :: Apache Software License
Classifier: Programming Language :: Python :: 3
Classifier: Programming Language :: Python :: 3.10
Classifier: Programming Language :: Python :: 3.11
Classifier: Programming Language :: Python :: 3.12
Classifier: Topic :: Scientific/Engineering :: Artificial Intelligence
Classifier: Topic :: Software Development :: Libraries :: Application Frameworks
Classifier: Topic :: Software Development :: Libraries :: Python Modules
Requires-Dist: lavague-contexts-openai (>=0.2.0,<0.3.0)
Requires-Dist: lavague-core (>=0.2.31,<0.3.0)
Requires-Dist: lavague-drivers-selenium (>=0.2.12,<0.3.0)
Requires-Dist: lavague-gradio (>=0.2.8,<0.3.0)
Project-URL: Documentation, https://docs.lavague.ai/en/latest/
Project-URL: Repository, https://github.com/lavague-ai/LaVague/
